{"이미지 정보":{"이미지 식별자":703986,"이미지 높이":1066,"이미지 파일명":"(191)IMG_1.jpg","이미지 너비":800},"데이터셋 정보":{"파일 생성일자":"2020-10-29 12:43:29","데이터셋 상세설명":{"렉트좌표":{"아우터":[{}],"하의":[{}],"원피스":[{}],"상의":[{"X좌표":256.5,"Y좌표":575.5,"가로":298,"세로":403}]},"폴리곤좌표":{"아우터":[{}],"하의":[{}],"원피스":[{}],"상의":[{"X좌표8":386.0,"X좌표9":416.0,"X좌표2":261.0,"X좌표3":257.0,"X좌표1":330.0,"X좌표6":332.0,"X좌표7":352.0,"X좌표4":270.0,"X좌표5":283.0,"Y좌표25":809.0,"Y좌표9":586.0,"Y좌표22":945.0,"Y좌표21":957.0,"Y좌표24":938.0,"Y좌표23":952.0,"Y좌표20":979.0,"X좌표19":474.0,"X좌표18":504.0,"X좌표17":534.0,"X좌표16":555.0,"X좌표15":547.0,"X좌표14":544.0,"X좌표13":536.0,"X좌표12":488.0,"X좌표11":447.0,"Y좌표4":724.0,"X좌표10":414.0,"Y좌표3":749.0,"Y좌표2":792.0,"Y좌표1":807.0,"Y좌표8":631.0,"Y좌표7":688.0,"Y좌표6":724.0,"Y좌표5":717.0,"Y좌표15":805.0,"Y좌표14":682.0,"Y좌표17":968.0,"Y좌표16":967.0,"Y좌표11":576.0,"Y좌표10":606.0,"Y좌표13":633.0,"Y좌표12":577.0,"X좌표25":335.0,"X좌표24":336.0,"X좌표23":351.0,"X좌표22":361.0,"X좌표21":363.0,"X좌표20":391.0,"Y좌표19":970.0,"Y좌표18":963.0}]},"라벨링":{"스타일":[{"스타일":"리조트"}],"아우터":[{}],"하의":[{}],"원피스":[{}],"상의":[{"기장":"롱","색상":"핑크","서브색상":"화이트","카테고리":"블라우스","옷깃":"숄칼라","디테일":["싱글브레스티드","포켓"],"소매기장":"긴팔","소재":["우븐"],"프린트":["깅엄"],"넥라인":"브이넥","핏":"노멀"}]}},"파일 번호":703986,"파일 이름":"(191)IMG_1.jpg"}}