{"이미지 정보":{"이미지 식별자":665288,"이미지 높이":800,"이미지 파일명":"1 (30448).jpg","이미지 너비":800},"데이터셋 정보":{"파일 생성일자":"2020-10-27 22:08:29","데이터셋 상세설명":{"렉트좌표":{"아우터":[{}],"하의":[{"X좌표":346.5,"Y좌표":358.9,"가로":157,"세로":390}],"원피스":[{}],"상의":[{"X좌표":330.5,"Y좌표":245.9,"가로":172,"세로":244}]},"폴리곤좌표":{"아우터":[{}],"하의":[{"Y좌표9":739.4,"X좌표17":352.0,"X좌표16":387.0,"X좌표15":426.0,"X좌표14":427.0,"X좌표13":432.0,"X좌표12":437.0,"X좌표11":439.0,"Y좌표4":362.4,"X좌표10":468.0,"Y좌표3":400.4,"Y좌표2":483.4,"Y좌표1":725.4,"Y좌표8":589.4,"Y좌표7":455.4,"Y좌표6":423.4,"Y좌표5":359.4,"Y좌표15":721.4,"Y좌표14":646.4,"X좌표8":504.0,"Y좌표17":722.4,"X좌표9":503.0,"Y좌표16":730.4,"Y좌표11":717.4,"Y좌표10":749.4,"Y좌표13":542.4,"Y좌표12":645.4,"X좌표2":352.0,"X좌표3":347.0,"X좌표1":357.0,"X좌표6":489.0,"X좌표7":488.0,"X좌표4":368.0,"X좌표5":465.0}],"원피스":[{}],"상의":[{"Y좌표9":254.4,"X좌표14":452.0,"X좌표13":470.0,"X좌표12":503.0,"X좌표11":476.0,"Y좌표4":484.4,"X좌표10":492.0,"Y좌표3":490.4,"Y좌표2":383.4,"Y좌표1":387.4,"Y좌표8":246.4,"Y좌표7":262.4,"Y좌표6":250.4,"Y좌표5":270.4,"Y좌표14":386.4,"X좌표8":454.0,"X좌표9":477.0,"Y좌표11":339.4,"Y좌표10":293.4,"Y좌표13":426.4,"Y좌표12":425.4,"X좌표2":384.0,"X좌표3":367.0,"X좌표1":451.0,"X좌표6":381.0,"X좌표7":403.0,"X좌표4":331.0,"X좌표5":338.0}]},"라벨링":{"스타일":[{"스타일":"매니시","서브스타일":"스트리트"}],"아우터":[{}],"하의":[{"기장":"발목","색상":"카키","카테고리":"팬츠","소재":["우븐"],"프린트":["무지"],"핏":"와이드"}],"원피스":[{}],"상의":[{"색상":"베이지","카테고리":"니트웨어","디테일":["단추"],"소매기장":"긴팔","소재":["니트"],"프린트":["무지"],"넥라인":"라운드넥","핏":"타이트"}]}},"파일 번호":665288,"파일 이름":"1 (30448).jpg"}}